oscar_python/__init__.py
oscar_python/_oidc.py
oscar_python/_utils.py
oscar_python/client.py
oscar_python/client_anon.py
oscar_python/default_client.py
oscar_python/local_test.py
oscar_python/storage.py
oscar_python/_providers/_minio.py
oscar_python/_providers/_onedata.py
oscar_python/_providers/_providers_base.py
oscar_python/_providers/_s3.py
oscar_python/_providers/_webdav.py
oscar_python-1.3.3.dist-info/licenses/LICENSE
oscar_python-1.3.3.dist-info/METADATA
oscar_python-1.3.3.dist-info/WHEEL
oscar_python-1.3.3.dist-info/top_level.txt
oscar_python-1.3.3.dist-info/RECORD
