Metadata-Version: 2.4
Name: oscar-python
Version: 1.3.3
Summary: Python client for OSCAR clusters
Author: GRyCAP - I3M - UPV
License: Apache-2.0
Project-URL: Homepage, https://github.com/grycap/oscar-python
Project-URL: Repository, https://github.com/grycap/oscar-python
Keywords: oscar,faas,serverless
Requires-Python: >=3.8
License-File: LICENSE
Requires-Dist: requests
Requires-Dist: webdavclient3>=3.14.6
Requires-Dist: boto3
Requires-Dist: pyyaml
Requires-Dist: aiohttp
Requires-Dist: liboidcagent
Provides-Extra: dev
Requires-Dist: pytest; extra == "dev"
Requires-Dist: pytest-cov; extra == "dev"
Dynamic: license-file
